<index>
    <Y>
        <link>11.html#York Timbers Ltd v SA Forestry Ltd (09/CAC/May01) [2001] ZACAC 3 (18 September 2001);</link>
        <link>12.html#York Timbers Ltd v SA Forestry Ltd (09/CAC/May01) [2001] ZACAC 3 (18 September 2001);</link>
    </Y>
    <C>
        <link>15.html#Competition Commission v Unilever PLC and Others (13/CAC/Jan02) [2002] ZACAC 1 (14 February 2002);</link>
        <link>16.html#Competition Commission v Unilever PLC and Others (13/CAC/Jan02) [2002] ZACAC 1 (14 February 2002);</link>
    </C>
    <D>
        <link>13.html#Distillers Corporation (SA) Ltd and Another v Bulmer (SA) (Pty) Ltd and Another (08/CAC/May01) [2001] ZACAC 4 (27</link>
        <link>14.html#Distillers Corporation (SA) Ltd and Another v Bulmer (SA) (Pty) Ltd and Another (08/CAC/May01) [2001] ZACAC 4 (27</link>
    </D>
    <G>
        <link>7.html#Glaxo Wellcome (Pty) Ltd Others v D. Terblanche Others (04/CAC/Oct00) [2000] ZACAC 2 (04 December 2000);</link>
        <link>8.html#Glaxo Wellcome (Pty) Ltd Others v D. Terblanche Others (04/CAC/Oct00) [2000] ZACAC 2 (04 December 2000);</link>
        <link>9.html#Glaxo Wellcome (Pty) Ltd Others v D. Terblanche Others (03/CAC/Oct00) [2001] ZACAC 2 (05 September 2001);</link>
        <link>10.html#Glaxo Wellcome (Pty) Ltd Others v D. Terblanche Others (03/CAC/Oct00) [2001] ZACAC 2 (05 September 2001);</link>
    </G>
</index>